openimages/__init__.py
openimages/download.py
openimages-0.0.1.dist-info/METADATA
openimages-0.0.1.dist-info/WHEEL
openimages-0.0.1.dist-info/entry_points.txt
openimages-0.0.1.dist-info/top_level.txt
openimages-0.0.1.dist-info/RECORD
