Metadata-Version: 2.1
Name: openimages
Version: 0.0.1
Summary: Tools for downloading computer vision datasets from Google's OpenImages dataset
Home-page: https://github.com/monocongo/openimages
Author: James Adams
Author-email: monocongo@gmail.com
License: UNKNOWN
Platform: UNKNOWN
Classifier: License :: OSI Approved :: MIT License
Classifier: Programming Language :: Python :: 3.6
Classifier: Programming Language :: Python :: 3.7
Classifier: Programming Language :: Python :: 3.8
Classifier: Operating System :: OS Independent
Provides: openimages
Requires-Python: >=3.6
Requires-Dist: boto3
Requires-Dist: cvdata
Requires-Dist: lxml
Requires-Dist: pandas
Requires-Dist: requests
Requires-Dist: tqdm
